fflogsapi/__init__.py
fflogsapi/client.py
fflogsapi/constants.py
fflogsapi/user_auth.py
fflogsapi/characters/__init__.py
fflogsapi/characters/character.py
fflogsapi/characters/client_extensions.py
fflogsapi/characters/queries.py
fflogsapi/data/__init__.py
fflogsapi/data/dataclasses.py
fflogsapi/data/page.py
fflogsapi/data/queries.py
fflogsapi/game/__init__.py
fflogsapi/game/client_extensions.py
fflogsapi/game/pages.py
fflogsapi/game/queries.py
fflogsapi/guilds/__init__.py
fflogsapi/guilds/client_extensions.py
fflogsapi/guilds/guild.py
fflogsapi/guilds/pages.py
fflogsapi/guilds/queries.py
fflogsapi/parsers/__init__.py
fflogsapi/prograce/__init__.py
fflogsapi/prograce/client_extensions.py
fflogsapi/prograce/queries.py
fflogsapi/reports/__init__.py
fflogsapi/reports/client_extensions.py
fflogsapi/reports/fight.py
fflogsapi/reports/pages.py
fflogsapi/reports/queries.py
fflogsapi/reports/report.py
fflogsapi/user/__init__.py
fflogsapi/user/client_extensions.py
fflogsapi/user/queries.py
fflogsapi/user/user.py
fflogsapi/util/__init__.py
fflogsapi/util/decorators.py
fflogsapi/util/filters.py
fflogsapi/util/gql_enums.py
fflogsapi/util/indexing.py
fflogsapi/world/__init__.py
fflogsapi/world/client_extensions.py
fflogsapi/world/encounter.py
fflogsapi/world/expansion.py
fflogsapi/world/pages.py
fflogsapi/world/queries.py
fflogsapi/world/region.py
fflogsapi/world/server.py
fflogsapi/world/zone.py
fflogsapi-2.1.3.dist-info/LICENSE
fflogsapi-2.1.3.dist-info/METADATA
fflogsapi-2.1.3.dist-info/WHEEL
fflogsapi-2.1.3.dist-info/top_level.txt
fflogsapi-2.1.3.dist-info/RECORD
