Metadata-Version: 2.1
Name: fflogsapi
Version: 2.1.3
Summary: Python client for the FF Logs v2 API
Author-email: Markus Wang Halvorsen <mwh@halvorsenfamilien.com>
Project-URL: Repository, https://github.com/halworsen/fflogsapi
Keywords: api,client,ffxiv,fflogs,lazy
Classifier: Development Status :: 5 - Production/Stable
Classifier: Intended Audience :: Developers
Classifier: License :: OSI Approved :: GNU General Public License v3 (GPLv3)
Classifier: Programming Language :: Python :: 3.9
Classifier: Topic :: Software Development :: Libraries
License-File: LICENSE
Requires-Dist: gql ~=3.4.0
Requires-Dist: oauthlib ~=3.2.2
Requires-Dist: requests-oauthlib ~=1.3.1
Requires-Dist: requests-toolbelt ~=0.10.1
Requires-Dist: cryptography ~=42.0.5
Requires-Dist: urllib3 ~=1.26.14
Provides-Extra: dev
Requires-Dist: flake8 ==6.0.0 ; extra == 'dev'
Requires-Dist: autopep8 ==2.0.1 ; extra == 'dev'
Requires-Dist: isort ==5.12.0 ; extra == 'dev'
Requires-Dist: removestar ==1.3.1 ; extra == 'dev'
Requires-Dist: sphinx ==7.2.5 ; extra == 'dev'
Provides-Extra: test
Requires-Dist: pytest ==7.2.1 ; extra == 'test'
Requires-Dist: pytest-cov ==4.0.0 ; extra == 'test'
